<?xml version="1.0" encoding="UTF-8"?>
<!DOCTYPE mapper PUBLIC "-//mybatis.org//DTD Mapper 3.0//EN" "http://mybatis.org/dtd/mybatis-3-mapper.dtd">
<mapper namespace="cn.liuxingwei.spring.boot.mapper.ProjectrepeatfeeMapper">
  <resultMap id="BaseResultMap" type="cn.liuxingwei.spring.boot.model.Projectrepeatfee">
    <!--
      WARNING - @mbg.generated
      This element is automatically generated by MyBatis Generator, do not modify.
    -->
    <id column="id" jdbcType="BIGINT" property="id" />
    <result column="user_id" jdbcType="BIGINT" property="userId" />
    <result column="user_name" jdbcType="VARCHAR" property="userName" />
    <result column="create_amount" jdbcType="DECIMAL" property="createAmount" />
    <result column="time" jdbcType="DATE" property="time" />
    <result column="amount" jdbcType="DECIMAL" property="amount" />
    <result column="type" jdbcType="TINYINT" property="type" />
    <result column="project_id" jdbcType="BIGINT" property="projectId" />
    <result column="project_name" jdbcType="VARCHAR" property="projectName" />
    <result column="project_invest_id" jdbcType="BIGINT" property="projectInvestId" />
  </resultMap>
  <delete id="deleteByPrimaryKey" parameterType="java.lang.Long">
    <!--
      WARNING - @mbg.generated
      This element is automatically generated by MyBatis Generator, do not modify.
    -->
    delete from t_project_repeat_fee
    where id = #{id,jdbcType=BIGINT}
  </delete>
  <insert id="insert" parameterType="cn.liuxingwei.spring.boot.model.Projectrepeatfee">
    <!--
      WARNING - @mbg.generated
      This element is automatically generated by MyBatis Generator, do not modify.
    -->
    <selectKey keyProperty="id" order="BEFORE" resultType="java.lang.Long">
      SELECT LAST_INSERT_ID()
    </selectKey>
    insert into t_project_repeat_fee (id, user_id, user_name, 
      create_amount, time, amount, 
      type, project_id, project_name, 
      project_invest_id)
    values (#{id,jdbcType=BIGINT}, #{userId,jdbcType=BIGINT}, #{userName,jdbcType=VARCHAR}, 
      #{createAmount,jdbcType=DECIMAL}, #{time,jdbcType=DATE}, #{amount,jdbcType=DECIMAL}, 
      #{type,jdbcType=TINYINT}, #{projectId,jdbcType=BIGINT}, #{projectName,jdbcType=VARCHAR}, 
      #{projectInvestId,jdbcType=BIGINT})
  </insert>
  <update id="updateByPrimaryKey" parameterType="cn.liuxingwei.spring.boot.model.Projectrepeatfee">
    <!--
      WARNING - @mbg.generated
      This element is automatically generated by MyBatis Generator, do not modify.
    -->
    update t_project_repeat_fee
    set user_id = #{userId,jdbcType=BIGINT},
      user_name = #{userName,jdbcType=VARCHAR},
      create_amount = #{createAmount,jdbcType=DECIMAL},
      time = #{time,jdbcType=DATE},
      amount = #{amount,jdbcType=DECIMAL},
      type = #{type,jdbcType=TINYINT},
      project_id = #{projectId,jdbcType=BIGINT},
      project_name = #{projectName,jdbcType=VARCHAR},
      project_invest_id = #{projectInvestId,jdbcType=BIGINT}
    where id = #{id,jdbcType=BIGINT}
  </update>
  <select id="selectByPrimaryKey" parameterType="java.lang.Long" resultMap="BaseResultMap">
    <!--
      WARNING - @mbg.generated
      This element is automatically generated by MyBatis Generator, do not modify.
    -->
    select id, user_id, user_name, create_amount, time, amount, type, project_id, project_name, 
    project_invest_id
    from t_project_repeat_fee
    where id = #{id,jdbcType=BIGINT}
  </select>
  <select id="selectAll" resultMap="BaseResultMap">
    <!--
      WARNING - @mbg.generated
      This element is automatically generated by MyBatis Generator, do not modify.
    -->
    select id, user_id, user_name, create_amount, time, amount, type, project_id, project_name, 
    project_invest_id
    from t_project_repeat_fee
  </select>
</mapper>